GEOSLAM/SLAM.py
GEOSLAM/__init__.py
GEOSLAM/version.py
GEOSLAM-0.0.2.dist-info/LICENSE
GEOSLAM-0.0.2.dist-info/METADATA
GEOSLAM-0.0.2.dist-info/WHEEL
GEOSLAM-0.0.2.dist-info/top_level.txt
GEOSLAM-0.0.2.dist-info/RECORD
